[
    {
        "rank": "No.1",
        "title": "베테랑2",
        "rate": "55.3%",
        "date": "2024.09.13",
        "imageURL": "https://img.cgv.co.kr/Movie/Thumbnail/Poster/000088/88488/88488_320.jpg"
    },
    {
        "rank": "No.2",
        "title": "정국: 아이 엠 스틸",
        "rate": "9.4%",
        "date": "2024.09.18",
        "imageURL": "https://img.cgv.co.kr/Movie/Thumbnail/Poster/000088/88687/88687_320.jpg"
    },
    {
        "rank": "No.3",
        "title": "임영웅ㅣ아임 히어로 더 스타디움",
        "rate": "6.3%",
        "date": "2024.08.28",
        "imageURL": "https://img.cgv.co.kr/Movie/Thumbnail/Poster/000088/88499/88499_320.jpg"
    },
    {
        "rank": "No.4",
        "title": "브레드이발소-빵스타의 탄생",
        "rate": "3.5%",
        "date": "2024.09.14",
        "imageURL": "https://img.cgv.co.kr/Movie/Thumbnail/Poster/000088/88485/88485_320.jpg"
    },
    {
        "rank": "No.5",
        "title": "요네즈 켄시 2023 투어 / 공상",
        "rate": "2.8%",
        "date": "2024.09.11",
        "imageURL": "https://img.cgv.co.kr/Movie/Thumbnail/Poster/000088/88651/88651_320.jpg"
    },
    {
        "rank": "No.6",
        "title": "안녕, 할부지",
        "rate": "2.4%",
        "date": "2024.09.04",
        "imageURL": "https://img.cgv.co.kr/Movie/Thumbnail/Poster/000088/88628/88628_320.jpg"
    },
    {
        "rank": "No.7",
        "title": "장손",
        "rate": "2.1%",
        "date": "2024.09.11",
        "imageURL": "https://img.cgv.co.kr/Movie/Thumbnail/Poster/000088/88529/88529_320.jpg"
    },
    {
        "rank": "No.8",
        "title": "그녀에게",
        "rate": "1.4%",
        "date": "2024.09.11",
        "imageURL": "https://img.cgv.co.kr/Movie/Thumbnail/Poster/000088/88530/88530_320.jpg"
    },
    {
        "rank": "No.9",
        "title": "RIIZE FAN-CON TOUR ＇RIIZING DAY＇ FINALE in CINEMAS",
        "rate": "1.4%",
        "date": "2024.09.13",
        "imageURL": "https://img.cgv.co.kr/Movie/Thumbnail/Poster/000088/88640/88640_320.jpg"
    },
    {
        "rank": "No.10",
        "title": "비틀쥬스 비틀쥬스",
        "rate": "1.4%",
        "date": "2024.09.04",
        "imageURL": "https://img.cgv.co.kr/Movie/Thumbnail/Poster/000088/88337/88337_320.jpg"
    },
    {
        "rank": "No.11",
        "title": "여름이 끝날 무렵의 라트라비아타",
        "rate": "1.3%",
        "date": "2024.09.11",
        "imageURL": "https://img.cgv.co.kr/Movie/Thumbnail/Poster/000088/88522/88522_320.jpg"
    },
    {
        "rank": "No.12",
        "title": "빅토리",
        "rate": "1.3%",
        "date": "2024.08.14",
        "imageURL": "https://img.cgv.co.kr/Movie/Thumbnail/Poster/000088/88380/88380_320.jpg"
    },
    {
        "rank": "No.13",
        "title": "[마이 아티 필름] 카리나 : 업",
        "rate": "0.9%",
        "date": "2024.09.11",
        "imageURL": "https://img.cgv.co.kr/Movie/Thumbnail/Poster/000088/88736/88736_320.jpg"
    },
    {
        "rank": "No.14",
        "title": "(라이브뷰잉) 프로젝트 세카이 4주년 감사제",
        "rate": "0.7%",
        "date": "2024.09.28",
        "imageURL": "https://img.cgv.co.kr/Movie/Thumbnail/Poster/000088/88660/88660_320.jpg"
    },
    {
        "rank": "No.15",
        "title": "트위스터스",
        "rate": "0.7%",
        "date": "2024.08.14",
        "imageURL": "https://img.cgv.co.kr/Movie/Thumbnail/Poster/000088/88442/88442_320.jpg"
    },
    {
        "rank": "No.16",
        "title": "2024 ZEROBASEONE THE FIRST TOUR TIMELESS WORLD IN SEOUL",
        "rate": "0.7%",
        "date": "2024.09.21",
        "imageURL": "https://img.cgv.co.kr/Movie/Thumbnail/Poster/000088/88681/88681_320.jpg"
    },
    {
        "rank": "No.17",
        "title": "에이리언- 로물루스",
        "rate": "0.7%",
        "date": "2024.08.14",
        "imageURL": "https://img.cgv.co.kr/Movie/Thumbnail/Poster/000088/88170/88170_320.jpg"
    },
    {
        "rank": "No.18",
        "title": "딸에 대하여",
        "rate": "0.7%",
        "date": "2024.09.04",
        "imageURL": "https://img.cgv.co.kr/Movie/Thumbnail/Poster/000088/88509/88509_320.jpg"
    },
    {
        "rank": "No.19",
        "title": "레드불 T1 다큐멘터리 : 함께 날아오르다",
        "rate": "0.6%",
        "date": "2024.09.04",
        "imageURL": "https://img.cgv.co.kr/Movie/Thumbnail/Poster/000088/88566/88566_320.jpg"
    },
    {
        "title": "그녀에게",
        "rate": "1.4%",
        "date": "2024.09.11",
        "imageURL": "https://img.cgv.co.kr/Movie/Thumbnail/Poster/000088/88530/88530_320.jpg"
    },
    {
        "title": "RIIZE FAN-CON TOUR ＇RIIZING DAY＇ FINALE in CINEMAS",
        "rate": "1.4%",
        "date": "2024.09.13",
        "imageURL": "https://img.cgv.co.kr/Movie/Thumbnail/Poster/000088/88640/88640_320.jpg"
    },
    {
        "title": "비틀쥬스 비틀쥬스",
        "rate": "1.4%",
        "date": "2024.09.04",
        "imageURL": "https://img.cgv.co.kr/Movie/Thumbnail/Poster/000088/88337/88337_320.jpg"
    },
    {
        "title": "여름이 끝날 무렵의 라트라비아타",
        "rate": "1.3%",
        "date": "2024.09.11",
        "imageURL": "https://img.cgv.co.kr/Movie/Thumbnail/Poster/000088/88522/88522_320.jpg"
    },
    {
        "title": "빅토리",
        "rate": "1.3%",
        "date": "2024.08.14",
        "imageURL": "https://img.cgv.co.kr/Movie/Thumbnail/Poster/000088/88380/88380_320.jpg"
    },
    {
        "title": "[마이 아티 필름] 카리나 : 업",
        "rate": "0.9%",
        "date": "2024.09.11",
        "imageURL": "https://img.cgv.co.kr/Movie/Thumbnail/Poster/000088/88736/88736_320.jpg"
    },
    {
        "title": "(라이브뷰잉) 프로젝트 세카이 4주년 감사제",
        "rate": "0.7%",
        "date": "2024.09.28",
        "imageURL": "https://img.cgv.co.kr/Movie/Thumbnail/Poster/000088/88660/88660_320.jpg"
    },
    {
        "title": "트위스터스",
        "rate": "0.7%",
        "date": "2024.08.14",
        "imageURL": "https://img.cgv.co.kr/Movie/Thumbnail/Poster/000088/88442/88442_320.jpg"
    },
    {
        "title": "2024 ZEROBASEONE THE FIRST TOUR TIMELESS WORLD IN SEOUL",
        "rate": "0.7%",
        "date": "2024.09.21",
        "imageURL": "https://img.cgv.co.kr/Movie/Thumbnail/Poster/000088/88681/88681_320.jpg"
    },
    {
        "title": "에이리언- 로물루스",
        "rate": "0.7%",
        "date": "2024.08.14",
        "imageURL": "https://img.cgv.co.kr/Movie/Thumbnail/Poster/000088/88170/88170_320.jpg"
    },
    {
        "title": "딸에 대하여",
        "rate": "0.7%",
        "date": "2024.09.04",
        "imageURL": "https://img.cgv.co.kr/Movie/Thumbnail/Poster/000088/88509/88509_320.jpg"
    },
    {
        "title": "레드불 T1 다큐멘터리 : 함께 날아오르다",
        "rate": "0.6%",
        "date": "2024.09.04",
        "imageURL": "https://img.cgv.co.kr/Movie/Thumbnail/Poster/000088/88566/88566_320.jpg"
    },
    {
        "title": "코마다 위스키 패밀리",
        "rate": "0.6%",
        "date": "2024.09.05",
        "imageURL": "https://img.cgv.co.kr/Movie/Thumbnail/Poster/000088/88536/88536_320.jpg"
    },
    {
        "title": "스픽 노 이블",
        "rate": "0.5%",
        "date": "2024.09.11",
        "imageURL": "https://img.cgv.co.kr/Movie/Thumbnail/Poster/000088/88370/88370_320.jpg"
    },
    {
        "title": "러빙 빈센트",
        "rate": "0.5%",
        "date": "2024.09.05",
        "imageURL": "https://img.cgv.co.kr/Movie/Thumbnail/Poster/000080/80117/80117_320.jpg"
    },
    {
        "title": "소년시절의 너",
        "rate": "0.4%",
        "date": "2024.08.28",
        "imageURL": "https://img.cgv.co.kr/Movie/Thumbnail/Poster/000083/83353/83353_320.jpg"
    },
    {
        "title": "극장판 블루 록 -에피소드 나기-",
        "rate": "0.4%",
        "date": "2024.08.21",
        "imageURL": "https://img.cgv.co.kr/Movie/Thumbnail/Poster/000088/88495/88495_320.jpg"
    },
    {
        "title": "사랑의 하츄핑",
        "rate": "0.4%",
        "date": "2024.08.07",
        "imageURL": "https://img.cgv.co.kr/Movie/Thumbnail/Poster/000088/88403/88403_320.jpg"
    },
    {
        "title": "세 가지 색-화이트",
        "rate": "0.4%",
        "date": "2024.09.11",
        "imageURL": "https://img.cgv.co.kr/Movie/Thumbnail/Poster/000083/83748/83748_320.jpg"
    },
    {
        "title": "파일럿",
        "rate": "0.3%",
        "date": "2024.07.31",
        "imageURL": "https://img.cgv.co.kr/Movie/Thumbnail/Poster/000088/88437/88437_320.jpg"
    },
    {
        "title": "새벽의 모든",
        "rate": "0.2%",
        "date": "2024.09.19",
        "imageURL": "https://img.cgv.co.kr/Movie/Thumbnail/Poster/000088/88527/88527_320.jpg"
    },
    {
        "title": "화양연화 리마스터링",
        "rate": "0.2%",
        "date": "2020.12.24",
        "imageURL": "https://img.cgv.co.kr/Movie/Thumbnail/Poster/000083/83963/83963_320.jpg"
    },
    {
        "title": "세 가지 색-블루",
        "rate": "0.2%",
        "date": "2024.09.04",
        "imageURL": "https://img.cgv.co.kr/Movie/Thumbnail/Poster/000083/83746/83746_320.jpg"
    },
    {
        "title": "중경삼림 리마스터링",
        "rate": "0.2%",
        "date": "2021.03.04",
        "imageURL": "https://img.cgv.co.kr/Movie/Thumbnail/Poster/000084/84277/84277_320.jpg"
    },
    {
        "title": "극장총집편 봇치 더 록! 전편",
        "rate": "0.2%",
        "date": "2024.08.07",
        "imageURL": "https://img.cgv.co.kr/Movie/Thumbnail/Poster/000088/88287/88287_320.jpg"
    },
    {
        "title": "위국일기",
        "rate": "0.2%",
        "date": "2024.10.02",
        "imageURL": "https://img.cgv.co.kr/Movie/Thumbnail/Poster/000088/88655/88655_320.jpg"
    },
    {
        "title": "세 가지 색-레드",
        "rate": "0.1%",
        "date": "2024.09.18",
        "imageURL": "https://img.cgv.co.kr/Movie/Thumbnail/Poster/000083/83747/83747_320.jpg"
    },
    {
        "title": "애프터썬",
        "rate": "0.1%",
        "date": "2024.08.28",
        "imageURL": "https://img.cgv.co.kr/Movie/Thumbnail/Poster/000086/86794/86794_320.jpg"
    },
    {
        "title": "트랜스포머 ONE",
        "rate": "0.1%",
        "date": "2024.09.25",
        "imageURL": "https://img.cgv.co.kr/Movie/Thumbnail/Poster/000088/88500/88500_320.jpg"
    },
    {
        "title": "비포 미드나잇",
        "rate": "0.1%",
        "date": "2024.09.04",
        "imageURL": "https://img.cgv.co.kr/Movie/Thumbnail/Poster/000076/76947/76947_320.jpg"
    },
    {
        "title": "캐시 아웃",
        "rate": "0.1%",
        "date": "2024.09.12",
        "imageURL": "https://img.cgv.co.kr/Movie/Thumbnail/Poster/000088/88661/88661_320.jpg"
    },
    {
        "title": "아비정전",
        "rate": "0.1%",
        "date": "2017.03.30",
        "imageURL": "https://img.cgv.co.kr/Movie/Thumbnail/Poster/000079/79755/79755_320.jpg"
    },
    {
        "title": "이매지너리",
        "rate": "0.1%",
        "date": "2024.08.28",
        "imageURL": "https://img.cgv.co.kr/Movie/Thumbnail/Poster/000088/88490/88490_320.jpg"
    },
    {
        "title": "죽고 싶지만 사랑은 하고 싶어",
        "rate": "0.1%",
        "date": "2024.09.04",
        "imageURL": "https://img.cgv.co.kr/Movie/Thumbnail/Poster/000088/88493/88493_320.jpg"
    },
    {
        "title": "비긴 어게인",
        "rate": "0.1%",
        "date": "2024.09.18",
        "imageURL": "https://img.cgv.co.kr/Movie/Thumbnail/Poster/000077/77772/77772_320.jpg"
    },
    {
        "title": "[토커바웃아트]패션과 미술 : 브랜드부터 현대미술까지",
        "rate": "0.0%",
        "date": "2024.09.25",
        "imageURL": "https://img.cgv.co.kr/Movie/Thumbnail/Poster/000088/88643/88643_320.jpg"
    },
    {
        "title": "한국이 싫어서",
        "rate": "0.0%",
        "date": "2024.08.28",
        "imageURL": "https://img.cgv.co.kr/Movie/Thumbnail/Poster/000088/88383/88383_320.jpg"
    },
    {
        "title": "늘봄가든",
        "rate": "0.0%",
        "date": "2024.08.21",
        "imageURL": "https://img.cgv.co.kr/Movie/Thumbnail/Poster/000088/88476/88476_320.jpg"
    },
    {
        "title": "세븐틴 투어 ‘팔로우’ 어게인 투 시네마",
        "rate": "0.0%",
        "date": "2024.08.14",
        "imageURL": "https://img.cgv.co.kr/Movie/Thumbnail/Poster/000088/88478/88478_320.jpg"
    },
    {
        "title": "행복의 나라",
        "rate": "0.0%",
        "date": "2024.08.14",
        "imageURL": "https://img.cgv.co.kr/Movie/Thumbnail/Poster/000088/88454/88454_320.jpg"
    },
    {
        "title": "[씨네뮤지엄] 바티칸 박물관",
        "rate": "0.0%",
        "date": "2024.09.13",
        "imageURL": "https://img.cgv.co.kr/Movie/Thumbnail/Poster/000087/87190/87190_320.jpg"
    },
    {
        "title": "사랑의 탐구",
        "rate": "0.0%",
        "date": "2024.09.18",
        "imageURL": "https://img.cgv.co.kr/Movie/Thumbnail/Poster/000088/88631/88631_320.jpg"
    },
    {
        "title": "52헤르츠 고래들",
        "rate": "0.0%",
        "date": "2024.09.04",
        "imageURL": "https://img.cgv.co.kr/Movie/Thumbnail/Poster/000088/88479/88479_320.jpg"
    },
    {
        "title": "원맨",
        "rate": "0.0%",
        "date": "2024.09.04",
        "imageURL": "https://img.cgv.co.kr/Movie/Thumbnail/Poster/000088/88521/88521_320.jpg"
    }
]