[
    {
        "rank": "1",
        "title": "육사오(6/45)",
        "price": "1,540캐시",
        "imageURL": "https://movie-phinf.pstatic.net/20220824_252/1661324514413czYBf_JPEG/movie_image.jpg?type=w320_r145"
    },
    {
        "rank": "2",
        "title": "인사이드 아웃(패키지상품 : 더빙판 + 부가영상 추가증정)",
        "price": "7,150캐시",
        "imageURL": "https://tvstore-phinf.pstatic.net/20211026_140/16352313679415fugQ_JPEG/15._.jpg?type=w320_r145"
    },
    {
        "rank": "3",
        "title": "엘리멘탈(패키지: 자막판+더빙판+부가영상+코멘터리)",
        "price": "7,150캐시",
        "imageURL": "https://tvstore-phinf.pstatic.net/20230806_132/1691315534742UTKOC_JPEG/_EC9798EBA6ACEBA998ED8388_%2BEAB5ADEBACB8%2BED8FACEC8AA4ED.jpg?type=w320_r145"
    },
    {
        "rank": "4",
        "title": "플래그 더 문",
        "price": "1,500캐시",
        "imageURL": "https://movie-phinf.pstatic.net/20160520_48/1463719352338lnHqy_JPEG/movie_image.jpg?type=w320_r145"
    },
    {
        "rank": "5",
        "title": "범죄도시4",
        "price": "11,000캐시",
        "imageURL": "https://s.pstatic.net/movie.phinf/20240425_256/17140073560223JK9r_JPEG/movie_image.jpg?type=w320_r145"
    },
    {
        "rank": "6",
        "title": "코코(패키지: 자막판+더빙판+부가영상)",
        "price": "7,150캐시",
        "imageURL": "https://tvstore-phinf.pstatic.net/20211026_79/1635229251764ygolt_JPEG/_Main.jpg?type=w320_r145"
    },
    {
        "rank": "7",
        "title": "패딩턴",
        "price": "1,200캐시",
        "imageURL": "https://tvstore-phinf.pstatic.net/20230331_39/1680243445718kxQk4_PNG/5BEC8B9CEBA6ACECA688ON5DPOSTER_5662.ED8CA8EB94A9ED84B4.png?type=w320_r145"
    },
    {
        "rank": "8",
        "title": "더 헌트",
        "price": "1,000캐시",
        "imageURL": "https://movie-phinf.pstatic.net/20130104_263/1357264883140Yx2Jn_JPEG/movie_image.jpg?type=w320_r145"
    },
    {
        "rank": "9",
        "title": "CJ7 - 장강7호",
        "price": "1,300캐시",
        "imageURL": "https://movie-phinf.pstatic.net/20111222_237/1324544105908Odv7z_JPEG/movie_image.jpg?type=w320_r145"
    },
    {
        "rank": "10",
        "title": "라따뚜이(패키지상품 : 더빙판 추가증정)",
        "price": "7,150캐시",
        "imageURL": "https://tvstore-phinf.pstatic.net/20211026_129/1635231265061toDLS_JPEG/08._.jpg?type=w320_r145"
    },
    {
        "rank": "11",
        "title": "명탐정 코난 VS 괴도 키드",
        "price": "7,700캐시",
        "imageURL": "https://s.pstatic.net/movie.phinf/20240605_48/1717561127727w5b9H_JPEG/movie_image.jpg?type=w320_r145"
    },
    {
        "rank": "12",
        "title": "퓨리오사: 매드맥스 사가",
        "price": "11,000캐시",
        "imageURL": "https://tvstore-phinf.pstatic.net/20240612_87/1718179591392OjDUN_JPEG/Furiosa_A_Mad_Max_Saga_V_DD_KA_TT_2000x3000_300dpi_KR.jpg?type=w320_r145"
    },
    {
        "rank": "13",
        "title": "말없는 소녀",
        "price": "1,540캐시",
        "imageURL": "https://s.pstatic.net/movie.phinf/20230504_11/1683193510206dCFgS_JPEG/movie_image.jpg?type=w320_r145"
    },
    {
        "rank": "14",
        "title": "소울메이트",
        "price": "1,540캐시",
        "imageURL": "https://s.pstatic.net/movie.phinf/20230315_171/1678842618052Q8wtc_JPEG/movie_image.jpg?type=w320_r145"
    },
    {
        "rank": "15",
        "title": "원피스 필름 레드",
        "price": "1,540캐시",
        "imageURL": "https://movie-phinf.pstatic.net/20221026_289/16667529839791pDb6_JPEG/movie_image.jpg?type=w320_r145"
    },
    {
        "rank": "16",
        "title": "미니언즈2",
        "price": "1,200캐시",
        "imageURL": "https://tvstore-phinf.pstatic.net/20220928_266/16643358179173iXVv_JPEG/MinionsRiseOfGru_2000x3000_kr_kor_keyart_full_digital_artwork_RGB_V1_sprk.jpg?type=w320_r145"
    },
    {
        "rank": "17",
        "title": "명탐정 코난: 할로윈의 신부",
        "price": "1,540캐시",
        "imageURL": "https://tvstore-phinf.pstatic.net/20221121_232/1669000553388XnVAs_JPEG/EC8898ECA095EB90A8_EBAA85ED8390ECA095ECBD94EB829CED95.jpg?type=w320_r145"
    },
    {
        "rank": "18",
        "title": "배드 가이즈",
        "price": "1,200캐시",
        "imageURL": "https://tvstore-phinf.pstatic.net/20220928_144/1664333556299cCx5n_JPEG/TheBadGuys_1000x1440_kr_kor_keyart_full_digital_artwork_RGB_V1_sprk.jpg?type=w320_r145"
    },
    {
        "rank": "19",
        "title": "고장난 론(패키지: 자막판+더빙판+부가영상)",
        "price": "7,150캐시",
        "imageURL": "https://tvstore-phinf.pstatic.net/20211224_183/1640328064042hGAE7_JPEG/__B_FN.jpg?type=w320_r145"
    },
    {
        "rank": "20",
        "title": "반도",
        "price": "1,000캐시",
        "imageURL": "https://movie-phinf.pstatic.net/20200624_137/15929908359489lOON_JPEG/movie_image.jpg?type=w320_r145"
    },
    {
        "rank": "21",
        "title": "날씨의 아이",
        "price": "1,400캐시",
        "imageURL": "https://movie-phinf.pstatic.net/20200515_153/1589521029136pyDNk_JPEG/movie_image.jpg?type=w320_r145"
    },
    {
        "rank": "22",
        "title": "극한직업",
        "price": "1,540캐시",
        "imageURL": "https://tvstore-phinf.pstatic.net/20230609_38/1686290074052MKHRN_PNG/5BEC8B9CEBA6ACECA688ON5DPOSTER_6099.EAB7B9ED959CECA781EC97.png?type=w320_r145"
    },
    {
        "rank": "23",
        "title": "위대한 쇼맨",
        "price": "5,500캐시",
        "imageURL": "https://movie-phinf.pstatic.net/20171218_47/1513561221134wvRja_JPEG/movie_image.jpg?type=w320_r145"
    },
    {
        "rank": "24",
        "title": "씽(패키지: 자막판+더빙판+부가영상)",
        "price": "5,000캐시",
        "imageURL": "https://movie-phinf.pstatic.net/20161208_30/1481172865937GitfC_JPEG/movie_image.jpg?type=w320_r145"
    },
    {
        "rank": "25",
        "title": "미니언즈",
        "price": "1,200캐시",
        "imageURL": "https://movie-phinf.pstatic.net/20150729_47/1438135916692zqgOj_JPEG/movie_image.jpg?type=w320_r145"
    },
    {
        "rank": "26",
        "title": "국제시장(본편)",
        "price": "1,540캐시",
        "imageURL": "https://tvstore-phinf.pstatic.net/20220913_88/1663046000836r0nkg_PNG/5BEC8B9CEBA6ACECA688ON5DPOSTER_4382.EAB5ADECA09CEC8B9CEC9E.png?type=w320_r145"
    },
    {
        "rank": "27",
        "title": "명량",
        "price": "1,540캐시",
        "imageURL": "https://tvstore-phinf.pstatic.net/20220913_241/16630459863285A2m0_PNG/5BEC8B9CEBA6ACECA688ON5DPOSTER_4381.EBAA85EB9F89.png?type=w320_r145"
    },
    {
        "rank": "28",
        "title": "7번방의 선물",
        "price": "1,000캐시",
        "imageURL": "https://movie-phinf.pstatic.net/20130118_115/1358472020816kP4vN_JPEG/movie_image.jpg?type=w320_r145"
    },
    {
        "rank": "29",
        "title": "방자전",
        "price": "1,540캐시",
        "imageURL": "https://movie-phinf.pstatic.net/20111223_214/1324614479718DP8fd_JPEG/movie_image.jpg?type=w320_r145"
    },
    {
        "rank": "30",
        "title": "쿵푸 팬더",
        "price": "1,200캐시",
        "imageURL": "https://movie-phinf.pstatic.net/20111222_227/13245572855713o8Lx_JPEG/movie_image.jpg?type=w320_r145"
    },
    {
        "rank": "31",
        "title": "동경 이야기",
        "price": "1,000캐시",
        "imageURL": "https://movie-phinf.pstatic.net/20140807_285/1407396855353S63rj_JPEG/movie_image.jpg?type=w320_r145"
    },
    {
        "rank": "32",
        "title": "짱구는 못말려: 어른제국의 역습!!",
        "price": "1,540캐시",
        "imageURL": "https://tvstore-phinf.pstatic.net/20230213_208/1676271225241HOOTR_PNG/5BEC8B9CEBA6ACECA688ON5DPOSTER_5389.ECA7B1EAB5ACEB8A94EBAA.png?type=w320_r145"
    },
    {
        "rank": "33",
        "title": "리틀 블루",
        "price": "5,000캐시",
        "imageURL": "https://tvstore-phinf.pstatic.net/20240621_84/1718953742519bumr2_JPEG/EBA6ACED8B80%2BEBB894EBA3A8%2BED8FACEC8AA4ED84B0%2B1.jpg?type=w320_r145"
    },
    {
        "rank": "34",
        "title": "프렌치 수프",
        "price": "11,000캐시",
        "imageURL": "https://s.pstatic.net/movie.phinf/20240620_284/1718862475382gU1hH_JPEG/movie_image.jpg?type=w320_r145"
    },
    {
        "rank": "35",
        "title": "원더랜드",
        "price": "7,700캐시",
        "imageURL": "https://s.pstatic.net/movie.phinf/20240509_23/1715231886407cOVc6_JPEG/movie_image.jpg?type=w320_r145"
    },
    {
        "rank": "36",
        "title": "그녀가 죽었다",
        "price": "11,000캐시",
        "imageURL": "https://s.pstatic.net/movie.phinf/20240516_147/1715830347927Txj0U_JPEG/movie_image.jpg?type=w320_r145"
    },
    {
        "rank": "37",
        "title": "이프: 상상의 친구",
        "price": "5,500캐시",
        "imageURL": "https://tvstore-phinf.pstatic.net/20240612_289/1718179739055z1Eyu_JPEG/IF_KR_800x1200.jpg?type=w320_r145"
    },
    {
        "rank": "38",
        "title": "악마와의 토크쇼",
        "price": "7,700캐시",
        "imageURL": "https://s.pstatic.net/movie.phinf/20240509_31/1715235948706HoyK3_JPEG/movie_image.jpg?type=w320_r145"
    },
    {
        "rank": "39",
        "title": "범죄도시4",
        "price": "16,390캐시",
        "imageURL": "https://s.pstatic.net/movie.phinf/20240425_256/17140073560223JK9r_JPEG/movie_image.jpg?type=w320_r145"
    },
    {
        "rank": "40",
        "title": "파묘",
        "price": "5,000캐시",
        "imageURL": "https://s.pstatic.net/movie.phinf/20240222_175/1708609058134r4oaq_JPEG/movie_image.jpg?type=w320_r145"
    },
    {
        "rank": "41",
        "title": "웡카(패키지: 자막판+더빙판+부가영상)",
        "price": "10,900캐시",
        "imageURL": "https://tvstore-phinf.pstatic.net/20240219_244/1708325233775UoPyr_JPEG/Wonka_STD_APO_V_DD_KA_TT_2160x2880_300dpi_KR.jpg?type=w320_r145"
    },
    {
        "rank": "42",
        "title": "정글번치: 월드투어",
        "price": "2,750캐시",
        "imageURL": "https://s.pstatic.net/movie.phinf/20240115_193/1705297777523B2ISN_JPEG/movie_image.jpg?type=w320_r145"
    },
    {
        "rank": "43",
        "title": "웡카",
        "price": "2,750캐시",
        "imageURL": "https://tvstore-phinf.pstatic.net/20240219_244/1708325233775UoPyr_JPEG/Wonka_STD_APO_V_DD_KA_TT_2160x2880_300dpi_KR.jpg?type=w320_r145"
    },
    {
        "rank": "44",
        "title": "신차원! 짱구는 못말려 더 무비 초능력 대결전 ~날아라 수제김밥~",
        "price": "5,500캐시",
        "imageURL": "https://tvstore-phinf.pstatic.net/20240312_59/1710213644239Clx2g_JPEG/3D%2BECA7B1EAB5AC%2BEAB7B9EC9EA5ED8C90_EBA994EC9DB8ED8FAC_E.jpg?type=w320_r145"
    },
    {
        "rank": "45",
        "title": "아쿠아맨과 로스트 킹덤",
        "price": "2,750캐시",
        "imageURL": "https://tvstore-phinf.pstatic.net/20240104_40/1704356043934hIjxt_JPEG/Aquaman_Lost_Kingdom_STD_APO_V_DD_KA_TT_2000x3000_300dpi_KR.jpg?type=w320_r145"
    },
    {
        "rank": "46",
        "title": "리빙: 어떤 인생",
        "price": "2,750캐시",
        "imageURL": "https://s.pstatic.net/movie.phinf/20231214_64/1702539931683HLwjl_JPEG/movie_image.jpg?type=w320_r145"
    },
    {
        "rank": "47",
        "title": "괴물",
        "price": "5,000캐시",
        "imageURL": "https://tvstore-phinf.pstatic.net/20240229_51/1709176558746Nbv5h_JPEG/Monster_TP_F_WEB_EAB09CEBB489EC9DBCECA09CEAB1B0.jpg?type=w320_r145"
    },
    {
        "rank": "48",
        "title": "서울의 봄",
        "price": "2,750캐시",
        "imageURL": "https://s.pstatic.net/movie.phinf/20231108_128/1699411327204OxmAK_JPEG/movie_image.jpg?type=w320_r145"
    },
    {
        "rank": "49",
        "title": "용감한 시민(가치봄영화:시청각장애인용)",
        "price": "2,750캐시",
        "imageURL": "https://s.pstatic.net/movie.phinf/20231025_58/1698242969177WPnLV_JPEG/movie_image.jpg?type=w320_r145"
    },
    {
        "rank": "50",
        "title": "용감한 시민",
        "price": "2,750캐시",
        "imageURL": "https://s.pstatic.net/movie.phinf/20231025_58/1698242969177WPnLV_JPEG/movie_image.jpg?type=w320_r145"
    },
    {
        "rank": "51",
        "title": "시수",
        "price": "2,500캐시",
        "imageURL": "https://s.pstatic.net/movie.phinf/20231009_68/1696858371495bjceF_JPEG/movie_image.jpg?type=w320_r145"
    },
    {
        "rank": "52",
        "title": "기억해, 우리가 사랑한 시간",
        "price": "2,500캐시",
        "imageURL": "https://tvstore-phinf.pstatic.net/20231024_144/1698126010821stMKV_JPEG/EAB8B0EC96B5ED95B4_EBA994EC9DB8ED8FACEC8AA4ED84B0.jpg?type=w320_r145"
    },
    {
        "rank": "53",
        "title": "킴스 비디오",
        "price": "2,500캐시",
        "imageURL": "https://s.pstatic.net/movie.phinf/20230830_143/1693356838903N0AwF_JPEG/movie_image.jpg?type=w320_r145"
    },
    {
        "rank": "54",
        "title": "더 문",
        "price": "2,750캐시",
        "imageURL": "https://s.pstatic.net/movie.phinf/20230803_160/1691042506911wyghG_JPEG/movie_image.jpg?type=w320_r145"
    },
    {
        "rank": "55",
        "title": "밀수",
        "price": "2,500캐시",
        "imageURL": "https://s.pstatic.net/movie.phinf/20230619_73/1687140044980ToOXr_JPEG/movie_image.jpg?type=w320_r145"
    },
    {
        "rank": "56",
        "title": "귀공자",
        "price": "1,540캐시",
        "imageURL": "https://s.pstatic.net/movie.phinf/20230621_28/1687336846998JAwMg_JPEG/movie_image.jpg?type=w320_r145"
    },
    {
        "rank": "57",
        "title": "범죄도시3",
        "price": "2,750캐시",
        "imageURL": "https://s.pstatic.net/movie.phinf/20230508_234/1683510751767I8t1j_JPEG/movie_image.jpg?type=w320_r145"
    },
    {
        "rank": "58",
        "title": "슈가 앤 스타",
        "price": "2,500캐시",
        "imageURL": "https://s.pstatic.net/movie.phinf/20230517_128/1684314299207vJgz5_JPEG/movie_image.jpg?type=w320_r145"
    },
    {
        "rank": "59",
        "title": "가디언즈 오브 갤럭시: Volume 3(부가영상+코멘터리 제공)",
        "price": "7,150캐시",
        "imageURL": "https://tvstore-phinf.pstatic.net/20230616_64/1686883405763jMRDx_JPEG/_EAB080EB9494EC96B8ECA688%2BEC98A4EBB88C%2BEAB0A4EB9FADEC8.jpg?type=w320_r145"
    },
    {
        "rank": "60",
        "title": "슈퍼 마리오 브라더스",
        "price": "1,200캐시",
        "imageURL": "https://tvstore-phinf.pstatic.net/20230414_83/16814513003274hFfa_JPEG/1920x2560_SUPER_MARIO_BROS_KR_KOR_Keyart_EPO_XYi.jpg?type=w320_r145"
    },
    {
        "rank": "61",
        "title": "슈퍼 마리오 브라더스(패키지: 자막판+더빙판)",
        "price": "5,000캐시",
        "imageURL": "https://tvstore-phinf.pstatic.net/20230414_83/16814513003274hFfa_JPEG/1920x2560_SUPER_MARIO_BROS_KR_KOR_Keyart_EPO_XYi.jpg?type=w320_r145"
    },
    {
        "rank": "62",
        "title": "리바운드",
        "price": "1,100캐시",
        "imageURL": "https://tvstore-phinf.pstatic.net/20230425_245/1682404359737zPLMG_JPEG/EBA994EC9DB8ED8FACEC8AA4ED84B0-001.jpg?type=w320_r145"
    },
    {
        "rank": "63",
        "title": "6번 칸",
        "price": "1,400캐시",
        "imageURL": "https://s.pstatic.net/movie.phinf/20230216_138/1676536267961cl57r_JPEG/movie_image.jpg?type=w320_r145"
    },
    {
        "rank": "64",
        "title": "스즈메의 문단속(패키지: 자막판+더빙판)",
        "price": "7,150캐시",
        "imageURL": "https://tvstore-phinf.pstatic.net/20231016_92/1697428201597Fa2qP_JPEG/SUZUME%2BMAIN%2BPOSTER%2B28429.jpg?type=w320_r145"
    },
    {
        "rank": "65",
        "title": "영웅",
        "price": "7,150캐시",
        "imageURL": "https://movie-phinf.pstatic.net/20221213_158/1670910727328mpqYu_JPEG/movie_image.jpg?type=w320_r145"
    },
    {
        "rank": "66",
        "title": "아바타: 물의 길(부가영상 제공)",
        "price": "7,150캐시",
        "imageURL": "https://tvstore-phinf.pstatic.net/20230316_101/1678940989922Y0fRg_JPEG/EB9494ECA688EB8B88_EC9584EBB094ED8380_EBACBCEC9D98%2BEAB.jpg?type=w320_r145"
    },
    {
        "rank": "67",
        "title": "스페이스 키드: 우주에서 살아남기",
        "price": "1,500캐시",
        "imageURL": "https://movie-phinf.pstatic.net/20221118_244/1668733391485u46NI_JPEG/movie_image.jpg?type=w320_r145"
    },
    {
        "rank": "68",
        "title": "에브리씽 에브리웨어 올 앳 원스",
        "price": "1,650캐시",
        "imageURL": "https://tvstore-phinf.pstatic.net/20230526_182/1685090019545qKkiq_PNG/5BEC8B9CEBA6ACECA688ON5DPOSTER_6000.EC9790EBB88CEBA6ACEC94.png?type=w320_r145"
    },
    {
        "rank": "69",
        "title": "성적표의 김민영",
        "price": "1,400캐시",
        "imageURL": "https://movie-phinf.pstatic.net/20220822_125/1661156316564qPyti_JPEG/movie_image.jpg?type=w320_r145"
    },
    {
        "rank": "70",
        "title": "육사오(6/45)(가치봄영화:시청각장애인용)",
        "price": "1,540캐시",
        "imageURL": "https://movie-phinf.pstatic.net/20220824_252/1661324514413czYBf_JPEG/movie_image.jpg?type=w320_r145"
    },
    {
        "rank": "71",
        "title": "썸머 필름을 타고!",
        "price": "1,400캐시",
        "imageURL": "https://movie-phinf.pstatic.net/20220627_271/1656311564441PQ0Jn_JPEG/movie_image.jpg?type=w320_r145"
    },
    {
        "rank": "72",
        "title": "마녀(魔女) Part2. The Other One",
        "price": "1,540캐시",
        "imageURL": "https://movie-phinf.pstatic.net/20220615_63/1655270906406BGdFF_JPEG/movie_image.jpg?type=w320_r145"
    },
    {
        "rank": "73",
        "title": "배드 가이즈",
        "price": "1,200캐시",
        "imageURL": "https://tvstore-phinf.pstatic.net/20220928_144/1664333556299cCx5n_JPEG/TheBadGuys_1000x1440_kr_kor_keyart_full_digital_artwork_RGB_V1_sprk.jpg?type=w320_r145"
    },
    {
        "rank": "74",
        "title": "이상한 나라의 수학자",
        "price": "2,750캐시",
        "imageURL": "https://movie-phinf.pstatic.net/20220210_27/16444726389021AWu6_JPEG/movie_image.jpg?type=w320_r145"
    },
    {
        "rank": "75",
        "title": "씽2게더",
        "price": "1,200캐시",
        "imageURL": "https://tvstore-phinf.pstatic.net/20220118_220/1642471073458re5VN_JPEG/2000x3000_Sing_2_KR_KOR_Digital_Keyart_XYi.jpg?type=w320_r145"
    },
    {
        "rank": "76",
        "title": "씽2게더",
        "price": "1,200캐시",
        "imageURL": "https://tvstore-phinf.pstatic.net/20220118_220/1642471073458re5VN_JPEG/2000x3000_Sing_2_KR_KOR_Digital_Keyart_XYi.jpg?type=w320_r145"
    },
    {
        "rank": "77",
        "title": "태일이",
        "price": "1,400캐시",
        "imageURL": "https://tvstore-phinf.pstatic.net/20231201_117/1701409476696lKsOj_PNG/5BEC8B9CEBA6ACECA688ON5DPOSTER_7025.ED839CEC9DBCEC9DB4.png?type=w320_r145"
    },
    {
        "rank": "78",
        "title": "애프터: 관계의 함정",
        "price": "1,400캐시",
        "imageURL": "https://movie-phinf.pstatic.net/20211018_155/1634523709170XHAvt_JPEG/movie_image.jpg?type=w320_r145"
    },
    {
        "rank": "79",
        "title": "극장판 짱구는 못말려: 격돌! 낙서왕국과 얼추 네 명의 용사들",
        "price": "1,540캐시",
        "imageURL": "https://movie-phinf.pstatic.net/20210915_97/16316820287099vGmY_JPEG/movie_image.jpg?type=w320_r145"
    },
    {
        "rank": "80",
        "title": "어웨이",
        "price": "1,400캐시",
        "imageURL": "https://movie-phinf.pstatic.net/20210721_25/1626834545261PP7u8_JPEG/movie_image.jpg?type=w320_r145"
    },
    {
        "rank": "81",
        "title": "모가디슈",
        "price": "1,400캐시",
        "imageURL": "https://tvstore-phinf.pstatic.net/20230116_290/1673839536751UUo0k_JPEG/5BEC8B9CEBA6ACECA688ON5DPOSTER_5227.EBAAA8EAB080EB9494EC8A.jpg?type=w320_r145"
    },
    {
        "rank": "82",
        "title": "이스케이프 룸 2: 노 웨이 아웃",
        "price": "1,300캐시",
        "imageURL": "https://tvstore-phinf.pstatic.net/20210826_36/1629943964659nTdae_JPEG/2__0714.jpg?type=w320_r145"
    },
    {
        "rank": "83",
        "title": "루카(패키지: 자막판+더빙판+부가영상)",
        "price": "7,150캐시",
        "imageURL": "https://tvstore-phinf.pstatic.net/20210723_257/1627004729177LxFjr_JPEG/LUCA_MediaPoster_MAIN-A.jpg?type=w320_r145"
    },
    {
        "rank": "84",
        "title": "사랑하고 사랑받고, 차고 차이고",
        "price": "1,500캐시",
        "imageURL": "https://movie-phinf.pstatic.net/20210312_260/1615527701881YmFce_JPEG/movie_image.jpg?type=w320_r145"
    },
    {
        "rank": "85",
        "title": "테넷",
        "price": "1,300캐시",
        "imageURL": "https://tvstore-phinf.pstatic.net/20201201_83/160680164490539Vqt_JPEG/TENET_V_DD_KA_TT_2000x2841_300dpi_KR.jpg?type=w320_r145"
    },
    {
        "rank": "86",
        "title": "쓰루 더 파이어",
        "price": "1,540캐시",
        "imageURL": "https://movie-phinf.pstatic.net/20200618_295/1592460251214z1wjQ_JPEG/movie_image.jpg?type=w320_r145"
    },
    {
        "rank": "87",
        "title": "트롤: 월드 투어",
        "price": "1,200캐시",
        "imageURL": "https://movie-phinf.pstatic.net/20200429_215/15881414327594O6hj_JPEG/movie_image.jpg?type=w320_r145"
    },
    {
        "rank": "88",
        "title": "언어의 정원",
        "price": "1,540캐시",
        "imageURL": "https://tvstore-phinf.pstatic.net/20231113_184/1699846154677iF73D_JPEG/kotonoha_PO.jpg?type=w320_r145"
    },
    {
        "rank": "89",
        "title": "기도의 힘",
        "price": "1,300캐시",
        "imageURL": "https://movie-phinf.pstatic.net/20200529_224/1590735807005fxqwX_JPEG/movie_image.jpg?type=w320_r145"
    },
    {
        "rank": "90",
        "title": "다크 워터스",
        "price": "1,000캐시",
        "imageURL": "https://movie-phinf.pstatic.net/20200219_277/15820765775925k14P_JPEG/movie_image.jpg?type=w320_r145"
    },
    {
        "rank": "91",
        "title": "정직한 후보",
        "price": "1,540캐시",
        "imageURL": "https://movie-phinf.pstatic.net/20200121_186/1579570188386BXMMG_JPEG/movie_image.jpg?type=w320_r145"
    },
    {
        "rank": "92",
        "title": "벌룬",
        "price": "1,400캐시",
        "imageURL": "https://movie-phinf.pstatic.net/20191226_175/1577338886314rAju2_JPEG/movie_image.jpg?type=w320_r145"
    },
    {
        "rank": "93",
        "title": "미드웨이",
        "price": "1,540캐시",
        "imageURL": "https://tvstore-phinf.pstatic.net/20230127_196/1674804940968c0Sqy_JPEG/5BEC8B9CEBA6ACECA688ON5DPOSTER_5308.EBAFB8EB939CEC9BA8EC9D.jpg?type=w320_r145"
    },
    {
        "rank": "94",
        "title": "백두산",
        "price": "1,540캐시",
        "imageURL": "https://tvstore-phinf.pstatic.net/20230526_138/1685090234509ynrLl_JPEG/5BEC8B9CEBA6ACECA688ON5DPOSTER_5981.EBB0B1EB9190EC82B0.jpg?type=w320_r145"
    },
    {
        "rank": "95",
        "title": "날씨의 아이",
        "price": "1,400캐시",
        "imageURL": "https://movie-phinf.pstatic.net/20200515_153/1589521029136pyDNk_JPEG/movie_image.jpg?type=w320_r145"
    },
    {
        "rank": "96",
        "title": "동물, 원",
        "price": "1,000캐시",
        "imageURL": "https://movie-phinf.pstatic.net/20190816_52/15659199538358bHdN_JPEG/movie_image.jpg?type=w320_r145"
    },
    {
        "rank": "97",
        "title": "명탐정 코난: 감청의 권",
        "price": "2,750캐시",
        "imageURL": "https://s.pstatic.net/movie.phinf/20190626_238/1561537910259KvwIR_JPEG/movie_image.jpg?type=w320_r145"
    },
    {
        "rank": "98",
        "title": "라이온 킹 (2019)(자막+더빙+부가영상+싱어롱 자막/더빙+코멘터리 제공)",
        "price": "5,500캐시",
        "imageURL": "https://tvstore-phinf.pstatic.net/20211026_31/1635229870839Kt8MH_JPEG/__Main.jpg?type=w320_r145"
    },
    {
        "rank": "99",
        "title": "애나벨 집으로",
        "price": "1,300캐시",
        "imageURL": "https://movie-phinf.pstatic.net/20190613_283/1560393273235OGHFz_JPEG/movie_image.jpg?type=w320_r145"
    },
    {
        "rank": "100",
        "title": "토이 스토리 4(패키지상품 : 더빙판+부가영상+코멘터리 추가증정)",
        "price": "7,150캐시",
        "imageURL": "https://tvstore-phinf.pstatic.net/20211026_13/1635229838603clNTv_JPEG/__4_Main_A.jpg?type=w320_r145"
    }
]