[
    {
        "title": "에이리언: 로물루스",
        "rank": "1",
        "imageURL": "https://file.cineq.co.kr/i.aspx?movieid=20249188&size=210"
    },
    {
        "title": "파일럿",
        "rank": "2",
        "imageURL": "https://file.cineq.co.kr/i.aspx?movieid=20224666&size=210"
    },
    {
        "title": "트위스터스",
        "rank": "3",
        "imageURL": "https://file.cineq.co.kr/i.aspx?movieid=20241337&size=210"
    },
    {
        "title": "늘봄가든",
        "rank": "4",
        "imageURL": "https://file.cineq.co.kr/i.aspx?movieid=20225969&size=210"
    },
    {
        "title": "행복의 나라",
        "rank": "5",
        "imageURL": "https://file.cineq.co.kr/i.aspx?movieid=20204271&size=210"
    },
    {
        "title": "소년시절의 너",
        "rank": "6",
        "imageURL": "https://file.cineq.co.kr/i.aspx?movieid=20200162&size=210"
    },
    {
        "title": "한국이 싫어서",
        "rank": "7",
        "imageURL": "https://file.cineq.co.kr/i.aspx?movieid=20226545&size=210"
    },
    {
        "title": "빅토리",
        "rank": "8",
        "imageURL": "https://file.cineq.co.kr/i.aspx?movieid=20231042&size=210"
    },
    {
        "title": "사랑의 하츄핑",
        "rank": "9",
        "imageURL": "https://file.cineq.co.kr/i.aspx?movieid=20249733&size=210"
    },
    {
        "title": "필사의 추격",
        "rank": "10",
        "imageURL": "https://file.cineq.co.kr/i.aspx?movieid=20229365&size=210"
    },
    {
        "title": "애프터썬",
        "rank": "11",
        "imageURL": "https://file.cineq.co.kr/i.aspx?movieid=20239877&size=210"
    },
    {
        "title": "스트레인저스: 챕터1",
        "rank": "12",
        "imageURL": "https://file.cineq.co.kr/i.aspx?movieid=20242403&size=210"
    },
    {
        "title": "극장판 : 기븐_히이라기 믹스",
        "rank": "13",
        "imageURL": "https://file.cineq.co.kr/i.aspx?movieid=20242836&size=210"
    },
    {
        "title": "명탐정 코난: 100만 달러의 펜타그램",
        "rank": "14",
        "imageURL": "https://file.cineq.co.kr/i.aspx?movieid=20240983&size=210"
    },
    {
        "title": "슈퍼배드 4",
        "rank": "15",
        "imageURL": "https://file.cineq.co.kr/i.aspx?movieid=20247440&size=210"
    },
    {
        "title": "희생",
        "rank": "16",
        "imageURL": "https://file.cineq.co.kr/i.aspx?movieid=20112979&size=210"
    },
    {
        "title": "비포 선셋",
        "rank": "17",
        "imageURL": "https://file.cineq.co.kr/i.aspx?movieid=20040689&size=210"
    },
    {
        "title": "프로이트의 라스트 세션",
        "rank": "18",
        "imageURL": "https://file.cineq.co.kr/i.aspx?movieid=20242421&size=210"
    },
    {
        "title": "문경",
        "rank": "19",
        "imageURL": "https://file.cineq.co.kr/i.aspx?movieid=20233234&size=210"
    },
    {
        "title": "가필드 더 무비",
        "rank": "20",
        "imageURL": "https://file.cineq.co.kr/i.aspx?movieid=20249305&size=210"
    },
    {
        "title": "러빙 빈센트",
        "rank": "21",
        "imageURL": "https://file.cineq.co.kr/i.aspx?movieid=20179942&size=210"
    },
    {
        "title": "베테랑2",
        "rank": "22",
        "imageURL": "https://file.cineq.co.kr/i.aspx?movieid=20239670&size=210"
    },
    {
        "title": "비틀쥬스 비틀쥬스",
        "rank": "23",
        "imageURL": "https://file.cineq.co.kr/i.aspx?movieid=20240669&size=210"
    },
    {
        "title": "안녕, 할부지",
        "rank": "24",
        "imageURL": "https://file.cineq.co.kr/i.aspx?movieid=20240925&size=210"
    },
    {
        "title": "둠벙",
        "rank": "25",
        "imageURL": "https://file.cineq.co.kr/i.aspx?movieid=20247435&size=210"
    },
    {
        "title": "공드리의 솔루션북",
        "rank": "26",
        "imageURL": "https://file.cineq.co.kr/i.aspx?movieid=20249356&size=210"
    }
]